climetlab_maelstrom_downscaling/__init__.py
climetlab_maelstrom_downscaling/downscaling_tier1.py
climetlab_maelstrom_downscaling/downscaling_tier2.py
climetlab_maelstrom_downscaling-0.4.0.dist-info/LICENSE
climetlab_maelstrom_downscaling-0.4.0.dist-info/METADATA
climetlab_maelstrom_downscaling-0.4.0.dist-info/WHEEL
climetlab_maelstrom_downscaling-0.4.0.dist-info/entry_points.txt
climetlab_maelstrom_downscaling-0.4.0.dist-info/top_level.txt
climetlab_maelstrom_downscaling-0.4.0.dist-info/zip-safe
climetlab_maelstrom_downscaling-0.4.0.dist-info/RECORD
