Metadata-Version: 2.1
Name: climetlab_maelstrom_downscaling
Version: 0.4.0
Summary: A dataset plugin for climetlab for the dataset maelstrom-downscaling.
Home-page: https://git.ecmwf.int/projects/MLFET/repos/maelstrom-downscaling-ap5/
Author: Michael Langguth, Bing Gong
Author-email: m.langguth@fz-juelich.de
License: Apache License Version 2.0
Keywords: meteorology
Classifier: Development Status :: 3 - Alpha
Classifier: Intended Audience :: Developers
Classifier: License :: OSI Approved :: Apache Software License
Classifier: Programming Language :: Python :: 3
Classifier: Programming Language :: Python :: 3.8
Classifier: Programming Language :: Python :: 3.9
Classifier: Programming Language :: Python :: 3.10
Classifier: Programming Language :: Python :: 3.11
Classifier: Programming Language :: Python :: Implementation :: CPython
Classifier: Programming Language :: Python :: Implementation :: PyPy
Classifier: Operating System :: OS Independent
License-File: LICENSE
Requires-Dist: climetlab >=0.9.0
